{"lastUsed":1692885351144,"path":"D:\/JP302\/JP302_VietHoang\/Bulit_2023","projectCount":2,"recentFiles":[{"path":"\/jsesystem\/src\/main\/java\/objects","parentWorkspace":"D:\/JP302\/JP302_VietHoang\/Bulit_2023","name":"Manager.java","lastModified":1676793754227,"locationURI":"file:\/D:\/JP302\/JP302_VietHoang\/Bulit_2023\/jsesystem\/src\/main\/java\/objects\/Manager.java"},{"path":"\/jsesystem\/src\/main\/java\/objects","parentWorkspace":"D:\/JP302_VietHoang\/Bulit_2023","name":"Student.java","lastModified":1676792524253,"locationURI":"file:\/D:\/JP302_VietHoang\/Bulit_2023\/jsesystem\/src\/main\/java\/objects\/Student.java"},{"path":"\/adsystem\/src\/main\/java\/jsoft","parentWorkspace":"D:\/JP302\/JP302_VietHoang\/Bulit_2023","name":"ShareControl.java","lastModified":1689584262474,"locationURI":"file:\/D:\/JP302\/JP302_VietHoang\/Bulit_2023\/adsystem\/src\/main\/java\/jsoft\/ShareControl.java"},{"path":"\/adsystem\/src\/main\/java\/jsoft","parentWorkspace":"D:\/JP302\/JP302_VietHoang\/Bulit_2023","name":"ConnectionPool.java","lastModified":1680680258624,"locationURI":"file:\/D:\/JP302\/JP302_VietHoang\/Bulit_2023\/adsystem\/src\/main\/java\/jsoft\/ConnectionPool.java"},{"path":"\/adsystem\/src\/main\/java\/jsoft\/ads\/article","parentWorkspace":"D:\/JP302\/JP302_VietHoang\/Bulit_2023","name":"Article.java","lastModified":1689147833936,"locationURI":"file:\/D:\/JP302\/JP302_VietHoang\/Bulit_2023\/adsystem\/src\/main\/java\/jsoft\/ads\/article\/Article.java"},{"path":"\/adsystem\/src\/main\/java\/jsoft\/ads\/main","parentWorkspace":"D:\/JP302\/JP302_VietHoang\/Bulit_2023","name":"Header.java","lastModified":1692763096577,"locationURI":"file:\/D:\/JP302\/JP302_VietHoang\/Bulit_2023\/adsystem\/src\/main\/java\/jsoft\/ads\/main\/Header.java"},{"path":"\/adsystem\/src\/main\/java\/jsoft\/ads\/user","parentWorkspace":"D:\/JP302\/JP302_VietHoang\/Bulit_2023","name":"UserLogin.java","lastModified":1692762635902,"locationURI":"file:\/D:\/JP302\/JP302_VietHoang\/Bulit_2023\/adsystem\/src\/main\/java\/jsoft\/ads\/user\/UserLogin.java"},{"path":"\/jsesystem\/src\/main\/java\/objects","parentWorkspace":"D:\/JP302_VietHoang\/Bulit_2023","name":"Address.java","lastModified":1689304854862,"locationURI":"file:\/D:\/JP302_VietHoang\/Bulit_2023\/jsesystem\/src\/main\/java\/objects\/Address.java"},{"path":"\/adsystem\/src\/main\/java\/jsoft\/ads\/user","parentWorkspace":"D:\/JP302\/JP302_VietHoang\/Bulit_2023","name":"UserControl.java","lastModified":1692784558549,"locationURI":"file:\/D:\/JP302\/JP302_VietHoang\/Bulit_2023\/adsystem\/src\/main\/java\/jsoft\/ads\/user\/UserControl.java"},{"path":"\/adsystem\/src\/main\/webapp\/adcss","parentWorkspace":"D:\/JP302\/JP302_VietHoang\/Bulit_2023","name":"style.css","lastModified":1692002553720,"locationURI":"file:\/D:\/JP302\/JP302_VietHoang\/Bulit_2023\/adsystem\/src\/main\/webapp\/adcss\/style.css"},{"path":"\/jsesystem\/src\/main\/java\/objects","parentWorkspace":"D:\/JP302_VietHoang\/Bulit_2023","name":"Person.java","lastModified":1689563802497,"locationURI":"file:\/D:\/JP302_VietHoang\/Bulit_2023\/jsesystem\/src\/main\/java\/objects\/Person.java"},{"path":"\/adsystem\/src\/main\/java\/jsoft\/ads\/user","parentWorkspace":"D:\/JP302\/JP302_VietHoang\/Bulit_2023","name":"USER_SORT_TYPE.java","lastModified":1684314260994,"locationURI":"file:\/D:\/JP302\/JP302_VietHoang\/Bulit_2023\/adsystem\/src\/main\/java\/jsoft\/ads\/user\/USER_SORT_TYPE.java"},{"path":"\/adsystem\/src\/main\/java\/jsoft\/ads\/user","parentWorkspace":"D:\/JP302\/JP302_VietHoang\/Bulit_2023","name":"UserLibrary.java","lastModified":1692778501919,"locationURI":"file:\/D:\/JP302\/JP302_VietHoang\/Bulit_2023\/adsystem\/src\/main\/java\/jsoft\/ads\/user\/UserLibrary.java"},{"path":"\/adsystem\/src\/main\/java\/jsoft\/library","parentWorkspace":"D:\/JP302\/JP302_VietHoang\/Bulit_2023","name":"Utilities.java","lastModified":1692613036249,"locationURI":"file:\/D:\/JP302\/JP302_VietHoang\/Bulit_2023\/adsystem\/src\/main\/java\/jsoft\/library\/Utilities.java"},{"path":"\/adsystem\/src\/main\/java\/jsoft\/ads\/section","parentWorkspace":"D:\/JP302\/JP302_VietHoang\/Bulit_2023","name":"Section.java","lastModified":1689584546784,"locationURI":"file:\/D:\/JP302\/JP302_VietHoang\/Bulit_2023\/adsystem\/src\/main\/java\/jsoft\/ads\/section\/Section.java"},{"path":"\/adsystem\/src\/main\/webapp\/adjs","parentWorkspace":"D:\/JP302\/JP302_VietHoang\/Bulit_2023","name":"main.js","lastModified":1692759920964,"locationURI":"file:\/D:\/JP302\/JP302_VietHoang\/Bulit_2023\/adsystem\/src\/main\/webapp\/adjs\/main.js"},{"path":"\/adsystem\/src\/main\/java\/jsoft","parentWorkspace":"D:\/JP302\/JP302_VietHoang\/Bulit_2023","name":"ConnectionPoolImpl.java","lastModified":1691565115414,"locationURI":"file:\/D:\/JP302\/JP302_VietHoang\/Bulit_2023\/adsystem\/src\/main\/java\/jsoft\/ConnectionPoolImpl.java"},{"path":"\/adsystem\/src\/main\/java\/jsoft\/ads\/user","parentWorkspace":"D:\/JP302\/JP302_VietHoang\/Bulit_2023","name":"UserLogout.java","lastModified":1692759721364,"locationURI":"file:\/D:\/JP302\/JP302_VietHoang\/Bulit_2023\/adsystem\/src\/main\/java\/jsoft\/ads\/user\/UserLogout.java"},{"path":"\/jsesystem\/src\/main\/java\/jse","parentWorkspace":"D:\/JP302\/JP302_VietHoang\/Bulit_2023","name":"Examples.java","lastModified":1679468468344,"locationURI":"file:\/D:\/JP302\/JP302_VietHoang\/Bulit_2023\/jsesystem\/src\/main\/java\/jse\/Examples.java"},{"path":"\/adsystem\/src\/main\/java\/jsoft\/ads\/section","parentWorkspace":"D:\/JP302\/JP302_VietHoang\/Bulit_2023","name":"SectionModel.java","lastModified":1691990906783,"locationURI":"file:\/D:\/JP302\/JP302_VietHoang\/Bulit_2023\/adsystem\/src\/main\/java\/jsoft\/ads\/section\/SectionModel.java"},{"path":"\/adsystem\/src\/main\/java\/jsoft\/library","parentWorkspace":"D:\/JP302\/JP302_VietHoang\/Bulit_2023","name":"UtilitiesDate.java","lastModified":1692605395427,"locationURI":"file:\/D:\/JP302\/JP302_VietHoang\/Bulit_2023\/adsystem\/src\/main\/java\/jsoft\/library\/UtilitiesDate.java"},{"path":"\/adsystem\/src\/main\/java\/jsoft\/ads\/basic","parentWorkspace":"D:\/JP302\/JP302_VietHoang\/Bulit_2023","name":"Basic.java","lastModified":1689584310406,"locationURI":"file:\/D:\/JP302\/JP302_VietHoang\/Bulit_2023\/adsystem\/src\/main\/java\/jsoft\/ads\/basic\/Basic.java"},{"path":"\/adsystem\/src\/main\/java\/jsoft\/ads\/section","parentWorkspace":"D:\/JP302\/JP302_VietHoang\/Bulit_2023","name":"SectionList.java","lastModified":1691999563446,"locationURI":"file:\/D:\/JP302\/JP302_VietHoang\/Bulit_2023\/adsystem\/src\/main\/java\/jsoft\/ads\/section\/SectionList.java"},{"path":"\/adsystem\/src\/main\/java\/jsoft\/ads\/advertise","parentWorkspace":"D:\/JP302\/JP302_VietHoang\/Bulit_2023","name":"Advertise.java","lastModified":1680663944341,"locationURI":"file:\/D:\/JP302\/JP302_VietHoang\/Bulit_2023\/adsystem\/src\/main\/java\/jsoft\/ads\/advertise\/Advertise.java"},{"path":"\/adsystem\/src\/main\/java\/jsoft\/ads\/category","parentWorkspace":"D:\/JP302\/JP302_VietHoang\/Bulit_2023","name":"CategoryControl.java","lastModified":1689585451275,"locationURI":"file:\/D:\/JP302\/JP302_VietHoang\/Bulit_2023\/adsystem\/src\/main\/java\/jsoft\/ads\/category\/CategoryControl.java"},{"path":"\/adsystem\/src\/main\/java\/jsoft\/ads\/section","parentWorkspace":"D:\/JP302\/JP302_VietHoang\/Bulit_2023","name":"SectionImplV2.java","lastModified":1690699641994,"locationURI":"file:\/D:\/JP302\/JP302_VietHoang\/Bulit_2023\/adsystem\/src\/main\/java\/jsoft\/ads\/section\/SectionImplV2.java"},{"path":"\/adsystem\/src\/main\/java\/jsoft\/ads\/user","parentWorkspace":"D:\/JP302\/JP302_VietHoang\/Bulit_2023","name":"MyServlet2.java","lastModified":1690364557008,"locationURI":"file:\/D:\/JP302\/JP302_VietHoang\/Bulit_2023\/adsystem\/src\/main\/java\/jsoft\/ads\/user\/MyServlet2.java"},{"path":"\/jsesystem\/src\/main\/java\/objects","parentWorkspace":"D:\/JP302\/JP302_VietHoang\/Bulit_2023","name":"BTTU.java","lastModified":1676798526546,"locationURI":"file:\/D:\/JP302\/JP302_VietHoang\/Bulit_2023\/jsesystem\/src\/main\/java\/objects\/BTTU.java"},{"path":"\/adsystem\/src\/main\/java\/jsoft\/objects","parentWorkspace":"D:\/JP302\/JP302_VietHoang\/Bulit_2023","name":"SectionObject.java","lastModified":1689580324318,"locationURI":"file:\/D:\/JP302\/JP302_VietHoang\/Bulit_2023\/adsystem\/src\/main\/java\/jsoft\/objects\/SectionObject.java"},{"path":"\/adsystem\/src\/main\/java\/jsoft\/objects","parentWorkspace":"D:\/JP302\/JP302_VietHoang\/Bulit_2023","name":"AdvertiseObject.java","lastModified":1680663446813,"locationURI":"file:\/D:\/JP302\/JP302_VietHoang\/Bulit_2023\/adsystem\/src\/main\/java\/jsoft\/objects\/AdvertiseObject.java"},{"path":"\/adsystem\/src\/main\/java\/jsoft\/ads\/category","parentWorkspace":"D:\/JP302\/JP302_VietHoang\/Bulit_2023","name":"CategoryImpl.java","lastModified":1689145155487,"locationURI":"file:\/D:\/JP302\/JP302_VietHoang\/Bulit_2023\/adsystem\/src\/main\/java\/jsoft\/ads\/category\/CategoryImpl.java"},{"path":"\/adsystem\/src\/main\/java\/jsoft\/ads\/section","parentWorkspace":"D:\/JP302\/JP302_VietHoang\/Bulit_2023","name":"SectionImpl.java","lastModified":1689137963187,"locationURI":"file:\/D:\/JP302\/JP302_VietHoang\/Bulit_2023\/adsystem\/src\/main\/java\/jsoft\/ads\/section\/SectionImpl.java"},{"path":"\/adsystem\/src\/main\/java\/jsoft\/objects","parentWorkspace":"D:\/JP302\/JP302_VietHoang\/Bulit_2023","name":"ArticleObject.java","lastModified":1680678924382,"locationURI":"file:\/D:\/JP302\/JP302_VietHoang\/Bulit_2023\/adsystem\/src\/main\/java\/jsoft\/objects\/ArticleObject.java"},{"path":"\/jsesystem\/src\/main\/java\/objects","parentWorkspace":"D:\/JP302\/JP302_VietHoang\/Bulit_2023","name":"CTH.java","lastModified":1676797958321,"locationURI":"file:\/D:\/JP302\/JP302_VietHoang\/Bulit_2023\/jsesystem\/src\/main\/java\/objects\/CTH.java"},{"path":"\/adsystem\/src\/main\/java\/jsoft\/objects","parentWorkspace":"D:\/JP302\/JP302_VietHoang\/Bulit_2023","name":"AccountObject.java","lastModified":1680662634798,"locationURI":"file:\/D:\/JP302\/JP302_VietHoang\/Bulit_2023\/adsystem\/src\/main\/java\/jsoft\/objects\/AccountObject.java"},{"path":"\/adsystem\/src\/main\/java\/jsoft\/objects","parentWorkspace":"D:\/JP302\/JP302_VietHoang\/Bulit_2023","name":"CategoryObject.java","lastModified":1680678922897,"locationURI":"file:\/D:\/JP302\/JP302_VietHoang\/Bulit_2023\/adsystem\/src\/main\/java\/jsoft\/objects\/CategoryObject.java"},{"path":"\/adsystem\/src\/main\/java\/jsoft\/ads\/user","parentWorkspace":"D:\/JP302\/JP302_VietHoang\/Bulit_2023","name":"UserModel.java","lastModified":1692885334142,"locationURI":"file:\/D:\/JP302\/JP302_VietHoang\/Bulit_2023\/adsystem\/src\/main\/java\/jsoft\/ads\/user\/UserModel.java"},{"path":"\/jsesystem\/src\/main\/java\/objects","parentWorkspace":"D:\/JP302\/JP302_VietHoang\/Bulit_2023","name":"BTTUImpl.java","lastModified":1677050427556,"locationURI":"file:\/D:\/JP302\/JP302_VietHoang\/Bulit_2023\/jsesystem\/src\/main\/java\/objects\/BTTUImpl.java"},{"path":"\/adsystem\/src\/main\/java\/jsoft\/ads\/user","parentWorkspace":"D:\/JP302\/JP302_VietHoang\/Bulit_2023","name":"UserProfiles.java","lastModified":1692885334142,"locationURI":"file:\/D:\/JP302\/JP302_VietHoang\/Bulit_2023\/adsystem\/src\/main\/java\/jsoft\/ads\/user\/UserProfiles.java"},{"path":"\/jsesystem\/src\/main\/java\/objects","parentWorkspace":"D:\/JP302_VietHoang\/Bulit_2023","name":"Employee.java","lastModified":1676792493913,"locationURI":"file:\/D:\/JP302_VietHoang\/Bulit_2023\/jsesystem\/src\/main\/java\/objects\/Employee.java"},{"path":"\/jsesystem\/src\/main\/java\/objects","parentWorkspace":"D:\/JP302\/JP302_VietHoang\/Bulit_2023","name":"ND.java","lastModified":1676798445041,"locationURI":"file:\/D:\/JP302\/JP302_VietHoang\/Bulit_2023\/jsesystem\/src\/main\/java\/objects\/ND.java"},{"path":"\/jsesystem\/src\/main\/java\/objects","parentWorkspace":"D:\/JP302\/JP302_VietHoang\/Bulit_2023","name":"EmployeeManager.java","lastModified":1676794070225,"locationURI":"file:\/D:\/JP302\/JP302_VietHoang\/Bulit_2023\/jsesystem\/src\/main\/java\/objects\/EmployeeManager.java"},{"path":"\/adsystem\/src\/main\/java\/jsoft\/ads\/section","parentWorkspace":"D:\/JP302\/JP302_VietHoang\/Bulit_2023","name":"SectionLibrary.java","lastModified":1691998273592,"locationURI":"file:\/D:\/JP302\/JP302_VietHoang\/Bulit_2023\/adsystem\/src\/main\/java\/jsoft\/ads\/section\/SectionLibrary.java"},{"path":"\/jsesystem\/src\/main\/java\/objects","parentWorkspace":"D:\/JP302\/JP302_VietHoang\/Bulit_2023","name":"TestManager.java","lastModified":1676796347780,"locationURI":"file:\/D:\/JP302\/JP302_VietHoang\/Bulit_2023\/jsesystem\/src\/main\/java\/objects\/TestManager.java"},{"path":"\/jsesystem\/src\/main\/java\/objects","parentWorkspace":"D:\/JP302\/JP302_VietHoang\/Bulit_2023","name":"TestPerson.java","lastModified":1676792837613,"locationURI":"file:\/D:\/JP302\/JP302_VietHoang\/Bulit_2023\/jsesystem\/src\/main\/java\/objects\/TestPerson.java"},{"path":"\/adsystem\/src\/main\/webapp\/adjs","parentWorkspace":"D:\/JP302\/JP302_VietHoang\/Bulit_2023","name":"bootstrap.bundle.min.js","lastModified":1692760004634,"locationURI":"file:\/D:\/JP302\/JP302_VietHoang\/Bulit_2023\/adsystem\/src\/main\/webapp\/adjs\/bootstrap.bundle.min.js"},{"path":"\/adsystem\/src\/main\/java\/jsoft\/objects","parentWorkspace":"D:\/JP302\/JP302_VietHoang\/Bulit_2023","name":"UserObject.java","lastModified":1684315180361,"locationURI":"file:\/D:\/JP302\/JP302_VietHoang\/Bulit_2023\/adsystem\/src\/main\/java\/jsoft\/objects\/UserObject.java"},{"path":"\/adsystem\/src\/main\/java\/jsoft\/ads\/section","parentWorkspace":"D:\/JP302\/JP302_VietHoang\/Bulit_2023","name":"SectionControl.java","lastModified":1689584752099,"locationURI":"file:\/D:\/JP302\/JP302_VietHoang\/Bulit_2023\/adsystem\/src\/main\/java\/jsoft\/ads\/section\/SectionControl.java"},{"path":"\/adsystem\/src\/main\/java\/jsoft\/ads\/category","parentWorkspace":"D:\/JP302\/JP302_VietHoang\/Bulit_2023","name":"CategoryList.java","lastModified":1691997045128,"locationURI":"file:\/D:\/JP302\/JP302_VietHoang\/Bulit_2023\/adsystem\/src\/main\/java\/jsoft\/ads\/category\/CategoryList.java"},{"path":"\/adsystem\/src\/main\/java\/jsoft\/ads\/article","parentWorkspace":"D:\/JP302\/JP302_VietHoang\/Bulit_2023","name":"ArticleModel.java","lastModified":1689584094887,"locationURI":"file:\/D:\/JP302\/JP302_VietHoang\/Bulit_2023\/adsystem\/src\/main\/java\/jsoft\/ads\/article\/ArticleModel.java"},{"path":"\/adsystem\/src\/main\/java\/jsoft\/ads\/main","parentWorkspace":"D:\/JP302\/JP302_VietHoang\/Bulit_2023","name":"Sidebar.java","lastModified":1692613036249,"locationURI":"file:\/D:\/JP302\/JP302_VietHoang\/Bulit_2023\/adsystem\/src\/main\/java\/jsoft\/ads\/main\/Sidebar.java"},{"path":"\/adsystem\/src\/main\/java\/jsoft\/ads\/user","parentWorkspace":"D:\/JP302\/JP302_VietHoang\/Bulit_2023","name":"User.java","lastModified":1692784016985,"locationURI":"file:\/D:\/JP302\/JP302_VietHoang\/Bulit_2023\/adsystem\/src\/main\/java\/jsoft\/ads\/user\/User.java"},{"path":"\/adsystem\/src\/main\/java\/jsoft\/ads\/main","parentWorkspace":"D:\/JP302\/JP302_VietHoang\/Bulit_2023","name":"Footer.java","lastModified":1692763087623,"locationURI":"file:\/D:\/JP302\/JP302_VietHoang\/Bulit_2023\/adsystem\/src\/main\/java\/jsoft\/ads\/main\/Footer.java"},{"path":"\/jsesystem\/src\/main\/java\/objects","parentWorkspace":"D:\/JP302\/JP302_VietHoang\/Bulit_2023","name":"NDImpl1.java","lastModified":1677050427556,"locationURI":"file:\/D:\/JP302\/JP302_VietHoang\/Bulit_2023\/jsesystem\/src\/main\/java\/objects\/NDImpl1.java"},{"path":"\/adsystem\/src\/main\/java\/jsoft\/ads\/main","parentWorkspace":"D:\/JP302\/JP302_VietHoang\/Bulit_2023","name":"View.java","lastModified":1691572707405,"locationURI":"file:\/D:\/JP302\/JP302_VietHoang\/Bulit_2023\/adsystem\/src\/main\/java\/jsoft\/ads\/main\/View.java"},{"path":"\/jsesystem\/src\/main\/java\/util","parentWorkspace":"D:\/JP302\/JP302_VietHoang\/Bulit_2023","name":"MyArrays.java","lastModified":1689563802497,"locationURI":"file:\/D:\/JP302\/JP302_VietHoang\/Bulit_2023\/jsesystem\/src\/main\/java\/util\/MyArrays.java"},{"path":"\/adsystem\/src\/main\/java\/jsoft\/objects","parentWorkspace":"D:\/JP302\/JP302_VietHoang\/Bulit_2023","name":"ComputerObject.java","lastModified":1680664894540,"locationURI":"file:\/D:\/JP302\/JP302_VietHoang\/Bulit_2023\/adsystem\/src\/main\/java\/jsoft\/objects\/ComputerObject.java"},{"path":"\/adsystem\/src\/main\/java\/jsoft\/ads\/user","parentWorkspace":"D:\/JP302\/JP302_VietHoang\/Bulit_2023","name":"USER_EDIT_TYPE.java","lastModified":1692783967245,"locationURI":"file:\/D:\/JP302\/JP302_VietHoang\/Bulit_2023\/adsystem\/src\/main\/java\/jsoft\/ads\/user\/USER_EDIT_TYPE.java"},{"path":"\/adsystem\/src\/main\/java\/jsoft\/ads\/basic","parentWorkspace":"D:\/JP302\/JP302_VietHoang\/Bulit_2023","name":"BasicImpl.java","lastModified":1690699641994,"locationURI":"file:\/D:\/JP302\/JP302_VietHoang\/Bulit_2023\/adsystem\/src\/main\/java\/jsoft\/ads\/basic\/BasicImpl.java"},{"path":"\/adsystem\/src\/main\/java\/jsoft\/objects","parentWorkspace":"D:\/JP302\/JP302_VietHoang\/Bulit_2023","name":"AgentObject.java","lastModified":1680664185202,"locationURI":"file:\/D:\/JP302\/JP302_VietHoang\/Bulit_2023\/adsystem\/src\/main\/java\/jsoft\/objects\/AgentObject.java"},{"path":"\/jsesystem\/src\/main\/java\/objects","parentWorkspace":"D:\/JP302\/JP302_VietHoang\/Bulit_2023","name":"StudentManager.java","lastModified":1676793998689,"locationURI":"file:\/D:\/JP302\/JP302_VietHoang\/Bulit_2023\/jsesystem\/src\/main\/java\/objects\/StudentManager.java"},{"path":"\/adsystem\/src\/main\/java\/jsoft\/ads\/category","parentWorkspace":"D:\/JP302\/JP302_VietHoang\/Bulit_2023","name":"CategoryLibrary.java","lastModified":1691997261758,"locationURI":"file:\/D:\/JP302\/JP302_VietHoang\/Bulit_2023\/adsystem\/src\/main\/java\/jsoft\/ads\/category\/CategoryLibrary.java"},{"path":"\/jsesystem\/src\/main\/java\/objects","parentWorkspace":"D:\/JP302\/JP302_VietHoang\/Bulit_2023","name":"GDS.java","lastModified":1676798092862,"locationURI":"file:\/D:\/JP302\/JP302_VietHoang\/Bulit_2023\/jsesystem\/src\/main\/java\/objects\/GDS.java"},{"path":"\/jsesystem\/src\/main\/java\/util","parentWorkspace":"D:\/JP302\/JP302_VietHoang\/Bulit_2023","name":"MyStrings.java","lastModified":1689563802497,"locationURI":"file:\/D:\/JP302\/JP302_VietHoang\/Bulit_2023\/jsesystem\/src\/main\/java\/util\/MyStrings.java"},{"path":"\/jsesystem\/src\/main\/java\/objects","parentWorkspace":"D:\/JP302\/JP302_VietHoang\/Bulit_2023","name":"NDImpl2.java","lastModified":1677050427556,"locationURI":"file:\/D:\/JP302\/JP302_VietHoang\/Bulit_2023\/jsesystem\/src\/main\/java\/objects\/NDImpl2.java"},{"path":"\/adsystem\/src\/main\/java\/jsoft\/ads\/article","parentWorkspace":"D:\/JP302\/JP302_VietHoang\/Bulit_2023","name":"ArticleImpl.java","lastModified":1689584094887,"locationURI":"file:\/D:\/JP302\/JP302_VietHoang\/Bulit_2023\/adsystem\/src\/main\/java\/jsoft\/ads\/article\/ArticleImpl.java"},{"path":"\/adsystem\/src\/main\/java\/jsoft\/ads\/category","parentWorkspace":"D:\/JP302\/JP302_VietHoang\/Bulit_2023","name":"CategoryModel.java","lastModified":1689585483620,"locationURI":"file:\/D:\/JP302\/JP302_VietHoang\/Bulit_2023\/adsystem\/src\/main\/java\/jsoft\/ads\/category\/CategoryModel.java"},{"path":"\/adsystem\/src\/main\/java\/jsoft\/ads\/user","parentWorkspace":"D:\/JP302\/JP302_VietHoang\/Bulit_2023","name":"UserImpl.java","lastModified":1692885334142,"locationURI":"file:\/D:\/JP302\/JP302_VietHoang\/Bulit_2023\/adsystem\/src\/main\/java\/jsoft\/ads\/user\/UserImpl.java"},{"path":"\/adsystem\/src\/main\/java\/jsoft\/ads\/user","parentWorkspace":"D:\/JP302\/JP302_VietHoang\/Bulit_2023","name":"UserList.java","lastModified":1692885334142,"locationURI":"file:\/D:\/JP302\/JP302_VietHoang\/Bulit_2023\/adsystem\/src\/main\/java\/jsoft\/ads\/user\/UserList.java"},{"path":"\/adsystem\/src\/main\/java\/jsoft\/ads\/account","parentWorkspace":"D:\/JP302\/JP302_VietHoang\/Bulit_2023","name":"Account.java","lastModified":1680663801233,"locationURI":"file:\/D:\/JP302\/JP302_VietHoang\/Bulit_2023\/adsystem\/src\/main\/java\/jsoft\/ads\/account\/Account.java"},{"path":"\/adsystem\/src\/main\/java\/jsoft\/ads\/user","parentWorkspace":"D:\/JP302\/JP302_VietHoang\/Bulit_2023","name":"MyServlet1.java","lastModified":1690364557008,"locationURI":"file:\/D:\/JP302\/JP302_VietHoang\/Bulit_2023\/adsystem\/src\/main\/java\/jsoft\/ads\/user\/MyServlet1.java"},{"path":"\/jsesystem\/src\/main\/java\/objects","parentWorkspace":"D:\/JP302\/JP302_VietHoang\/Bulit_2023","name":"CTX.java","lastModified":1676797824230,"locationURI":"file:\/D:\/JP302\/JP302_VietHoang\/Bulit_2023\/jsesystem\/src\/main\/java\/objects\/CTX.java"},{"path":"\/adsystem\/src\/main\/java\/jsoft\/ads\/category","parentWorkspace":"D:\/JP302\/JP302_VietHoang\/Bulit_2023","name":"Category.java","lastModified":1689585135510,"locationURI":"file:\/D:\/JP302\/JP302_VietHoang\/Bulit_2023\/adsystem\/src\/main\/java\/jsoft\/ads\/category\/Category.java"},{"path":"\/jsesystem\/src\/main\/java\/objects","parentWorkspace":"D:\/JP302\/JP302_VietHoang\/Bulit_2023","name":"TestInterface.java","lastModified":1677050427556,"locationURI":"file:\/D:\/JP302\/JP302_VietHoang\/Bulit_2023\/jsesystem\/src\/main\/java\/objects\/TestInterface.java"},{"path":"\/adsystem\/src\/main\/java\/jsoft\/ads\/category","parentWorkspace":"D:\/JP302\/JP302_VietHoang\/Bulit_2023","name":"CategoryImplV2.java","lastModified":1690699641994,"locationURI":"file:\/D:\/JP302\/JP302_VietHoang\/Bulit_2023\/adsystem\/src\/main\/java\/jsoft\/ads\/category\/CategoryImplV2.java"},{"path":"\/jsesystem\/src\/main\/java\/hwk","parentWorkspace":"D:\/JP302_VietHoang\/Bulit_2023","name":"Hwk1.java","lastModified":1676790093117,"locationURI":"file:\/D:\/JP302_VietHoang\/Bulit_2023\/jsesystem\/src\/main\/java\/hwk\/Hwk1.java"},{"path":"\/adsystem\/src\/main\/java\/jsoft\/ads\/main","parentWorkspace":"D:\/JP302\/JP302_VietHoang\/Bulit_2023","name":"Error.java","lastModified":1692885334142,"locationURI":"file:\/D:\/JP302\/JP302_VietHoang\/Bulit_2023\/adsystem\/src\/main\/java\/jsoft\/ads\/main\/Error.java"},{"path":"\/adsystem\/src\/main\/java\/jsoft\/library","parentWorkspace":"D:\/JP302\/JP302_VietHoang\/Bulit_2023","name":"UtilitiesText.java","lastModified":1692604536746,"locationURI":"file:\/D:\/JP302\/JP302_VietHoang\/Bulit_2023\/adsystem\/src\/main\/java\/jsoft\/library\/UtilitiesText.java"}]}